unchained_auth/__init__.py
unchained_auth/admin.py
unchained_auth/apps.py
unchained_auth/models.py
unchained_auth/serializers.py
unchained_auth/tests.py
unchained_auth/urls.py
unchained_auth/migrations/__init__.py
unchained_auth/views/__init__.py
unchained_auth/views/main.py
unchained_auth/views/phone.py
unchained_auth/views/social.py
unchained_chat/__init__.py
unchained_chat/admin.py
unchained_chat/apps.py
unchained_chat/consumers.py
unchained_chat/inlines.py
unchained_chat/models.py
unchained_chat/routing.py
unchained_chat/serializers.py
unchained_chat/tests.py
unchained_chat/urls.py
unchained_chat/views.py
unchained_chat/migrations/__init__.py
unchained_notification/__init__.py
unchained_notification/admin.py
unchained_notification/apps.py
unchained_notification/models.py
unchained_notification/serializers.py
unchained_notification/tests.py
unchained_notification/urls.py
unchained_notification/views.py
unchained_notification/migrations/__init__.py
django_unchained_apps-1.dist-info/LICENSE
django_unchained_apps-1.dist-info/METADATA
django_unchained_apps-1.dist-info/WHEEL
django_unchained_apps-1.dist-info/top_level.txt
django_unchained_apps-1.dist-info/RECORD
